avro/LICENSE
avro/NOTICE
avro/__init__.py
avro/datafile.py
avro/io.py
avro/ipc.py
avro/protocol.py
avro/schema.py
avro/tool.py
avro/txipc.py
avro_cwl-1.8.9.data/scripts/avro
avro_cwl-1.8.9.dist-info/LICENSE.txt
avro_cwl-1.8.9.dist-info/METADATA
avro_cwl-1.8.9.dist-info/NOTICE.txt
avro_cwl-1.8.9.dist-info/WHEEL
avro_cwl-1.8.9.dist-info/top_level.txt
avro_cwl-1.8.9.dist-info/RECORD
