Metadata-Version: 2.1
Name: avro-cwl
Version: 1.8.9
Summary: Avro is a serialization and RPC framework.
Home-page: UNKNOWN
Author: Common Workflow Langauge
License: Apache License 2.0
Keywords: avro serialization rpc
Platform: UNKNOWN
Requires-Dist: future
Provides-Extra: snappy
Requires-Dist: python-snappy ; extra == 'snappy'
